kogniserver/__init__.py
kogniserver/adm.py
kogniserver/async.py
kogniserver/client.py
kogniserver/pubsub.py
kogniserver/rpc.py
kogniserver/services.py
kogniserver/twist.py
kogniserver-0.3.1.dist-info/LICENSE
kogniserver-0.3.1.dist-info/METADATA
kogniserver-0.3.1.dist-info/WHEEL
kogniserver-0.3.1.dist-info/entry_points.txt
kogniserver-0.3.1.dist-info/top_level.txt
kogniserver-0.3.1.dist-info/RECORD
